{
  "summary": {
    "shared_overlays": [
      "turquoise",
      "rose",
      "tan",
      "gold",
      "fuchsia",
      "lavender",
      "peach",
      "mauve",
      "navy",
      "beige",
      "violet",
      "aqua",
      "sand",
      "coral",
      "rust",
      "magenta",
      "lilac",
      "wine",
      "taupe",
      "teal"
    ],
    "shared_basics": [
      "orange",
      "red",
      "gray",
      "purple",
      "brown",
      "pink",
      "green",
      "blue",
      "white",
      "yellow"
    ],
    "total_comparisons": 30
  },
  "comparisons": [
    {
      "color": "aqua",
      "xkcd_rgb": [
        62,
        206,
        189
      ],
      "xkcd_hue": 172.93673674592478,
      "xkcd_count": 23317,
      "centore_munsell": "7.44BG 6.18/3.37",
      "centore_hue": 206.784,
      "centore_value": 6.18,
      "centore_chroma": 3.37,
      "hue_difference": -33.847263254075216,
      "xkcd_value_approx": 6.8189434187124265,
      "value_difference": 0.6389434187124268,
      "xkcd_chroma_approx": 8.39523986841628,
      "chroma_difference": 5.025239868416279
    },
    {
      "color": "beige",
      "xkcd_rgb": [
        211,
        192,
        133
      ],
      "xkcd_hue": 45.483311871738074,
      "xkcd_count": 14322,
      "centore_munsell": "6.66YR 6.15/3.40",
      "centore_hue": 59.976,
      "centore_value": 6.15,
      "centore_chroma": 3.4,
      "hue_difference": -14.492688128261925,
      "xkcd_value_approx": 7.536079478986121,
      "value_difference": 1.3860794789861206,
      "xkcd_chroma_approx": 4.464713882557579,
      "chroma_difference": 1.0647138825575788
    },
    {
      "color": "blue",
      "xkcd_rgb": [
        55,
        97,
        198
      ],
      "xkcd_hue": 222.4235925859452,
      "xkcd_count": 288015,
      "centore_munsell": "0.56PB 4.69/4.64",
      "centore_hue": 254.016,
      "centore_value": 4.69,
      "centore_chroma": 4.64,
      "hue_difference": -31.592407414054804,
      "xkcd_value_approx": 3.7415931561571036,
      "value_difference": -0.9484068438428968,
      "xkcd_chroma_approx": 8.651496142877816,
      "chroma_difference": 4.011496142877816
    },
    {
      "color": "brown",
      "xkcd_rgb": [
        136,
        90,
        44
      ],
      "xkcd_hue": 29.796888303717935,
      "xkcd_count": 75812,
      "centore_munsell": "2.84YR 3.95/3.70",
      "centore_hue": 46.224,
      "centore_value": 3.95,
      "centore_chroma": 3.7,
      "hue_difference": -16.42711169628206,
      "xkcd_value_approx": 3.7762834200804263,
      "value_difference": -0.1737165799195739,
      "xkcd_chroma_approx": 8.15893038658557,
      "chroma_difference": 4.45893038658557
    },
    {
      "color": "coral",
      "xkcd_rgb": [
        230,
        100,
        92
      ],
      "xkcd_hue": 3.349650574860732,
      "xkcd_count": 2260,
      "centore_munsell": "6.53R 5.84/8.28",
      "centore_hue": 23.508000000000003,
      "centore_value": 5.84,
      "centore_chroma": 8.28,
      "hue_difference": -20.15834942513927,
      "xkcd_value_approx": 4.988034322401527,
      "value_difference": -0.8519656775984732,
      "xkcd_chroma_approx": 7.171711339253751,
      "chroma_difference": -1.1082886607462488
    },
    {
      "color": "fuchsia",
      "xkcd_rgb": [
        209,
        46,
        168
      ],
      "xkcd_hue": 315.0862935568183,
      "xkcd_count": 3471,
      "centore_munsell": "4.78RP 4.09/10.33",
      "centore_hue": 341.208,
      "centore_value": 4.09,
      "centore_chroma": 10.33,
      "hue_difference": -26.121706443181722,
      "xkcd_value_approx": 3.4925141356110294,
      "value_difference": -0.5974858643889704,
      "xkcd_chroma_approx": 9.385785758722339,
      "chroma_difference": -0.9442142412776615
    },
    {
      "color": "gold",
      "xkcd_rgb": [
        207,
        176,
        40
      ],
      "xkcd_hue": 49.1196160451388,
      "xkcd_count": 6265,
      "centore_munsell": "9.79YR 6.39/7.35",
      "centore_hue": 71.244,
      "centore_value": 6.39,
      "centore_chroma": 7.35,
      "hue_difference": -22.1243839548612,
      "xkcd_value_approx": 6.7767859699857596,
      "value_difference": 0.38678596998575987,
      "xkcd_chroma_approx": 9.704371052145492,
      "chroma_difference": 2.354371052145492
    },
    {
      "color": "gray",
      "xkcd_rgb": [
        143,
        147,
        143
      ],
      "xkcd_hue": 120.15508885298861,
      "xkcd_count": 18241,
      "centore_munsell": "9.62P 5.25/0.55",
      "centore_hue": 322.632,
      "centore_value": 5.25,
      "centore_chroma": 0.55,
      "hue_difference": 157.52308885298862,
      "xkcd_value_approx": 5.719071046801484,
      "value_difference": 0.46907104680148404,
      "xkcd_chroma_approx": 0.35989673150825596,
      "chroma_difference": -0.19010326849174408
    },
    {
      "color": "green",
      "xkcd_rgb": [
        74,
        185,
        68
      ],
      "xkcd_hue": 116.67815172047423,
      "xkcd_count": 314172,
      "centore_munsell": "2.04G 5.33/4.75",
      "centore_hue": 151.344,
      "centore_value": 5.33,
      "centore_chroma": 4.75,
      "hue_difference": -34.66584827952576,
      "xkcd_value_approx": 6.013399224229115,
      "value_difference": 0.6833992242291149,
      "xkcd_chroma_approx": 7.611072794203284,
      "chroma_difference": 2.8610727942032836
    },
    {
      "color": "lavender",
      "xkcd_rgb": [
        177,
        126,
        208
      ],
      "xkcd_hue": 277.0274150420259,
      "xkcd_count": 25800,
      "centore_munsell": "5.61P 5.37/4.79",
      "centore_hue": 308.196,
      "centore_value": 5.37,
      "centore_chroma": 4.79,
      "hue_difference": -31.168584957974133,
      "xkcd_value_approx": 5.608631923088616,
      "value_difference": 0.23863192308861603,
      "xkcd_chroma_approx": 4.710972536529488,
      "chroma_difference": -0.0790274634705117
    },
    {
      "color": "lilac",
      "xkcd_rgb": [
        179,
        123,
        209
      ],
      "xkcd_hue": 278.9814350820907,
      "xkcd_count": 15703,
      "centore_munsell": "7.75P 5.61/4.83",
      "centore_hue": 315.9,
      "centore_value": 5.61,
      "centore_chroma": 4.83,
      "hue_difference": -36.91856491790929,
      "xkcd_value_approx": 5.5230323897144675,
      "value_difference": -0.08696761028553279,
      "xkcd_chroma_approx": 4.94011360952235,
      "chroma_difference": 0.11011360952235005
    },
    {
      "color": "magenta",
      "xkcd_rgb": [
        200,
        39,
        152
      ],
      "xkcd_hue": 317.84762663361704,
      "xkcd_count": 43724,
      "centore_munsell": "3.82RP 3.37/9.39",
      "centore_hue": 337.752,
      "centore_value": 3.37,
      "centore_chroma": 9.39,
      "hue_difference": -19.90437336638297,
      "xkcd_value_approx": 3.2012580073580987,
      "value_difference": -0.16874199264190137,
      "xkcd_chroma_approx": 9.651915353951821,
      "chroma_difference": 0.26191535395182086
    },
    {
      "color": "mauve",
      "xkcd_rgb": [
        167,
        94,
        142
      ],
      "xkcd_hue": 320.75307566779315,
      "xkcd_count": 19149,
      "centore_munsell": "1.19RP 5.15/3.85",
      "centore_hue": 328.284,
      "centore_value": 5.15,
      "centore_chroma": 3.85,
      "hue_difference": -7.530924332206837,
      "xkcd_value_approx": 4.436211088891142,
      "value_difference": -0.7137889111088587,
      "xkcd_chroma_approx": 5.201368757489506,
      "chroma_difference": 1.3513687574895061
    },
    {
      "color": "navy",
      "xkcd_rgb": [
        32,
        45,
        104
      ],
      "xkcd_hue": 229.15379307812285,
      "xkcd_count": 7213,
      "centore_munsell": "7.26PB 2.11/3.61",
      "centore_hue": 278.136,
      "centore_value": 2.11,
      "centore_chroma": 3.61,
      "hue_difference": -48.98220692187718,
      "xkcd_value_approx": 1.813201478811405,
      "value_difference": -0.29679852118859484,
      "xkcd_chroma_approx": 8.315501876361065,
      "chroma_difference": 4.705501876361065
    },
    {
      "color": "orange",
      "xkcd_rgb": [
        228,
        122,
        38
      ],
      "xkcd_hue": 26.647587049664764,
      "xkcd_count": 52200,
      "centore_munsell": "2.50YR 5.69/8.86",
      "centore_hue": 45.0,
      "centore_value": 5.69,
      "centore_chroma": 8.86,
      "hue_difference": -18.352412950335236,
      "xkcd_value_approx": 5.44230310299752,
      "value_difference": -0.24769689700248065,
      "xkcd_chroma_approx": 10.023636656586916,
      "chroma_difference": 1.1636366565869167
    },
    {
      "color": "peach",
      "xkcd_rgb": [
        238,
        165,
        119
      ],
      "xkcd_hue": 23.369621135081672,
      "xkcd_count": 12023,
      "centore_munsell": "2.89YR 7.03/5.86",
      "centore_hue": 46.404,
      "centore_value": 7.03,
      "centore_chroma": 5.86,
      "hue_difference": -23.03437886491833,
      "xkcd_value_approx": 6.959473488232522,
      "value_difference": -0.07052651176747826,
      "xkcd_chroma_approx": 5.968913201230366,
      "chroma_difference": 0.10891320123036596
    },
    {
      "color": "pink",
      "xkcd_rgb": [
        227,
        91,
        169
      ],
      "xkcd_hue": 325.7454878665433,
      "xkcd_count": 131013,
      "centore_munsell": "0.70R 5.76/7.88",
      "centore_hue": 2.5199999999999996,
      "centore_value": 5.76,
      "centore_chroma": 7.88,
      "hue_difference": -36.77451213345671,
      "xkcd_value_approx": 4.930200041696206,
      "value_difference": -0.829799958303794,
      "xkcd_chroma_approx": 7.168214695886654,
      "chroma_difference": -0.711785304113346
    },
    {
      "color": "purple",
      "xkcd_rgb": [
        142,
        53,
        173
      ],
      "xkcd_hue": 284.40049396421614,
      "xkcd_count": 249199,
      "centore_munsell": "6.81P 3.53/6.45",
      "centore_hue": 312.516,
      "centore_value": 3.53,
      "centore_chroma": 6.45,
      "hue_difference": -28.11550603578388,
      "xkcd_value_approx": 3.155406693146803,
      "value_difference": -0.3745933068531966,
      "xkcd_chroma_approx": 8.323611560304204,
      "chroma_difference": 1.8736115603042043
    },
    {
      "color": "red",
      "xkcd_rgb": [
        204,
        38,
        44
      ],
      "xkcd_hue": 357.73581925688285,
      "xkcd_count": 69928,
      "centore_munsell": "4.27R 3.79/8.82",
      "centore_hue": 15.371999999999998,
      "centore_value": 3.79,
      "centore_chroma": 8.82,
      "hue_difference": -17.636180743117166,
      "xkcd_value_approx": 2.8904631659230446,
      "value_difference": -0.8995368340769554,
      "xkcd_chroma_approx": 9.760008625556708,
      "chroma_difference": 0.9400086255567075
    },
    {
      "color": "rose",
      "xkcd_rgb": [
        213,
        98,
        129
      ],
      "xkcd_hue": 343.72589146796093,
      "xkcd_count": 8810,
      "centore_munsell": "0.47R 4.99/7.69",
      "centore_hue": 1.692,
      "centore_value": 4.99,
      "centore_chroma": 7.69,
      "hue_difference": -17.966108532039073,
      "xkcd_value_approx": 4.883512160423761,
      "value_difference": -0.1064878395762392,
      "xkcd_chroma_approx": 6.476039691059263,
      "chroma_difference": -1.2139603089407371
    },
    {
      "color": "rust",
      "xkcd_rgb": [
        172,
        73,
        37
      ],
      "xkcd_hue": 15.716684518491833,
      "xkcd_count": 3170,
      "centore_munsell": "9.42R 3.95/7.37",
      "centore_hue": 33.912,
      "centore_value": 3.95,
      "centore_chroma": 7.37,
      "hue_difference": -18.195315481508167,
      "xkcd_value_approx": 3.575730507824581,
      "value_difference": -0.37426949217541905,
      "xkcd_chroma_approx": 9.404129209621994,
      "chroma_difference": 2.0341292096219936
    },
    {
      "color": "sand",
      "xkcd_rgb": [
        211,
        187,
        107
      ],
      "xkcd_hue": 46.54791356553886,
      "xkcd_count": 3685,
      "centore_munsell": "7.60YR 6.26/3.19",
      "centore_hue": 63.36,
      "centore_value": 6.26,
      "centore_chroma": 3.19,
      "hue_difference": -16.812086434461136,
      "xkcd_value_approx": 7.315443648069811,
      "value_difference": 1.0554436480698115,
      "xkcd_chroma_approx": 5.927184372259757,
      "chroma_difference": 2.737184372259757
    },
    {
      "color": "tan",
      "xkcd_rgb": [
        203,
        172,
        103
      ],
      "xkcd_hue": 41.43730680013425,
      "xkcd_count": 23977,
      "centore_munsell": "6.30YR 5.23/4.07",
      "centore_hue": 58.68,
      "centore_value": 5.23,
      "centore_chroma": 4.07,
      "hue_difference": -17.242693199865748,
      "xkcd_value_approx": 6.818954173566661,
      "value_difference": 1.5889541735666608,
      "xkcd_chroma_approx": 5.899344637128473,
      "chroma_difference": 1.8293446371284725
    },
    {
      "color": "taupe",
      "xkcd_rgb": [
        175,
        156,
        115
      ],
      "xkcd_hue": 41.54009835445436,
      "xkcd_count": 4210,
      "centore_munsell": "3.25YR 4.68/1.42",
      "centore_hue": 47.7,
      "centore_value": 4.68,
      "centore_chroma": 1.42,
      "hue_difference": -6.159901645545645,
      "xkcd_value_approx": 6.164193444180523,
      "value_difference": 1.484193444180523,
      "xkcd_chroma_approx": 4.138096344580465,
      "chroma_difference": 2.7180963445804647
    },
    {
      "color": "teal",
      "xkcd_rgb": [
        57,
        179,
        159
      ],
      "xkcd_hue": 170.26467647975264,
      "xkcd_count": 57128,
      "centore_munsell": "1.56B 3.32/4.53",
      "centore_hue": 221.61599999999999,
      "centore_value": 3.32,
      "centore_chroma": 4.53,
      "hue_difference": -51.35132352024735,
      "xkcd_value_approx": 5.94925820270133,
      "value_difference": 2.62925820270133,
      "xkcd_chroma_approx": 8.198863564753449,
      "chroma_difference": 3.6688635647534484
    },
    {
      "color": "turquoise",
      "xkcd_rgb": [
        54,
        195,
        178
      ],
      "xkcd_hue": 172.90059166442126,
      "xkcd_count": 26313,
      "centore_munsell": "1.61B 5.45/5.92",
      "centore_hue": 221.796,
      "centore_value": 5.45,
      "centore_chroma": 5.92,
      "hue_difference": -48.895408335578736,
      "xkcd_value_approx": 6.424582641697274,
      "value_difference": 0.9745826416972738,
      "xkcd_chroma_approx": 8.69331706256531,
      "chroma_difference": 2.77331706256531
    },
    {
      "color": "violet",
      "xkcd_rgb": [
        143,
        60,
        181
      ],
      "xkcd_hue": 281.2005101479182,
      "xkcd_count": 32806,
      "centore_munsell": "7.00P 3.80/6.16",
      "centore_hue": 313.2,
      "centore_value": 3.8,
      "centore_chroma": 6.16,
      "hue_difference": -31.99948985208181,
      "xkcd_value_approx": 3.4016489566112362,
      "value_difference": -0.3983510433887636,
      "xkcd_chroma_approx": 8.007288896568568,
      "chroma_difference": 1.8472888965685677
    },
    {
      "color": "white",
      "xkcd_rgb": [
        225,
        227,
        218
      ],
      "xkcd_hue": 73.97506523630054,
      "xkcd_count": 2427,
      "centore_munsell": "2.07Y 8.01/2.02",
      "centore_hue": 79.452,
      "centore_value": 8.01,
      "centore_chroma": 2.02,
      "hue_difference": -5.476934763699461,
      "xkcd_value_approx": 8.84912643221277,
      "value_difference": 0.8391264322127707,
      "xkcd_chroma_approx": 0.45135937823758854,
      "chroma_difference": -1.5686406217624116
    },
    {
      "color": "wine",
      "xkcd_rgb": [
        134,
        32,
        69
      ],
      "xkcd_hue": 338.0974183998595,
      "xkcd_count": 1559,
      "centore_munsell": "2.69R 2.98/4.85",
      "centore_hue": 9.684000000000001,
      "centore_value": 2.98,
      "centore_chroma": 4.85,
      "hue_difference": -31.586581600140505,
      "xkcd_value_approx": 2.2066987586310987,
      "value_difference": -0.7733012413689013,
      "xkcd_chroma_approx": 9.151417747675353,
      "chroma_difference": 4.3014177476753535
    },
    {
      "color": "yellow",
      "xkcd_rgb": [
        227,
        221,
        54
      ],
      "xkcd_hue": 58.1593002014805,
      "xkcd_count": 44073,
      "centore_munsell": "2.64Y 7.44/7.98",
      "centore_hue": 81.504,
      "centore_value": 7.44,
      "centore_chroma": 7.98,
      "hue_difference": -23.344699798519507,
      "xkcd_value_approx": 8.247853914205619,
      "value_difference": 0.8078539142056185,
      "xkcd_chroma_approx": 9.137364511010823,
      "chroma_difference": 1.1573645110108224
    }
  ],
  "bias_analysis": {
    "hue": {
      "name": "Hue",
      "n": 30,
      "mean": -19.31182860433474,
      "std": 35.444299766655455,
      "min": -51.35132352024735,
      "max": 157.52308885298862,
      "t_statistic": 2.9842666445391446,
      "systematic": true
    },
    "value": {
      "name": "Value",
      "n": 30,
      "mean": 0.17566294643164934,
      "std": 0.8831190162763628,
      "min": -0.9484068438428968,
      "max": 2.62925820270133,
      "t_statistic": 1.0894857488645295,
      "systematic": false
    },
    "chroma": {
      "name": "Chroma",
      "n": 30,
      "mean": 1.584729341505016,
      "std": 1.8930985404904557,
      "min": -1.5686406217624116,
      "max": 5.025239868416279,
      "t_statistic": 4.585033421755899,
      "systematic": true
    }
  },
  "xkcd_centroids": {
    "turquoise": {
      "rgb": [
        53.755558089157454,
        195.07969444761144,
        178.35773191958347
      ],
      "hue_angle": 172.90059166442126,
      "count": 26313
    },
    "gold": {
      "rgb": [
        206.52817238627296,
        176.24102154828412,
        39.509337589784515
      ],
      "hue_angle": 49.1196160451388,
      "count": 6265
    },
    "pink": {
      "rgb": [
        226.82177341179883,
        91.32950928533809,
        168.68319937716103
      ],
      "hue_angle": 325.7454878665433,
      "count": 131013
    },
    "tan": {
      "rgb": [
        203.1993160111774,
        172.29390666054968,
        103.30408307961797
      ],
      "hue_angle": 41.43730680013425,
      "count": 23977
    },
    "rose": {
      "rgb": [
        212.64120317820658,
        97.88513053348467,
        129.01101021566402
      ],
      "hue_angle": 343.72589146796093,
      "count": 8810
    },
    "fuchsia": {
      "rgb": [
        208.85883030826852,
        45.50014405070585,
        167.784212042639
      ],
      "hue_angle": 315.0862935568183,
      "count": 3471
    },
    "blue": {
      "rgb": [
        55.219169140496156,
        97.01270767147544,
        197.88838775758208
      ],
      "hue_angle": 222.4235925859452,
      "count": 288015
    },
    "lavender": {
      "rgb": [
        176.81949612403102,
        126.40317829457365,
        208.09883720930233
      ],
      "hue_angle": 277.0274150420259,
      "count": 25800
    },
    "peach": {
      "rgb": [
        237.60384263494967,
        165.45030358479582,
        119.41744988771521
      ],
      "hue_angle": 23.369621135081672,
      "count": 12023
    },
    "orange": {
      "rgb": [
        228.40197318007662,
        122.34971264367816,
        37.617107279693485
      ],
      "hue_angle": 26.647587049664764,
      "count": 52200
    },
    "mauve": {
      "rgb": [
        166.56023813253955,
        94.36513656065591,
        141.58906470311766
      ],
      "hue_angle": 320.75307566779315,
      "count": 19149
    },
    "purple": {
      "rgb": [
        141.6583694156076,
        52.94783686932933,
        172.82560122632916
      ],
      "hue_angle": 284.40049396421614,
      "count": 249199
    },
    "navy": {
      "rgb": [
        31.783585193400803,
        44.75058921391931,
        103.51559683904063
      ],
      "hue_angle": 229.15379307812285,
      "count": 7213
    },
    "beige": {
      "rgb": [
        211.46480938416423,
        192.42919983242564,
        132.78732020667505
      ],
      "hue_angle": 45.483311871738074,
      "count": 14322
    },
    "violet": {
      "rgb": [
        143.4334268121685,
        60.33938913613363,
        181.34862525147838
      ],
      "hue_angle": 281.2005101479182,
      "count": 32806
    },
    "white": {
      "rgb": [
        224.7045735475896,
        226.6905644829007,
        218.1639884631232
      ],
      "hue_angle": 73.97506523630054,
      "count": 2427
    },
    "red": {
      "rgb": [
        203.7243593410365,
        38.028400640658965,
        44.28116062235442
      ],
      "hue_angle": 357.73581925688285,
      "count": 69928
    },
    "brown": {
      "rgb": [
        136.37074605603334,
        89.69689495066744,
        43.65079406954044
      ],
      "hue_angle": 29.796888303717935,
      "count": 75812
    },
    "aqua": {
      "rgb": [
        61.79199725522151,
        205.7013337907964,
        188.7601749796286
      ],
      "hue_angle": 172.93673674592478,
      "count": 23317
    },
    "sand": {
      "rgb": [
        210.75142469470828,
        187.41275440976935,
        106.65454545454546
      ],
      "hue_angle": 46.54791356553886,
      "count": 3685
    },
    "coral": {
      "rgb": [
        229.8929203539823,
        100.16946902654867,
        92.49911504424779
      ],
      "hue_angle": 3.349650574860732,
      "count": 2260
    },
    "green": {
      "rgb": [
        74.34229339342781,
        185.45747552296194,
        67.82994665342551
      ],
      "hue_angle": 116.67815172047423,
      "count": 314172
    },
    "rust": {
      "rgb": [
        172.12145110410094,
        72.56687697160883,
        37.233753943217664
      ],
      "hue_angle": 15.716684518491833,
      "count": 3170
    },
    "gray": {
      "rgb": [
        142.68039032947755,
        147.09188092758072,
        142.6917932130914
      ],
      "hue_angle": 120.15508885298861,
      "count": 18241
    },
    "magenta": {
      "rgb": [
        200.3380751989754,
        39.200896532796634,
        152.4061385051688
      ],
      "hue_angle": 317.84762663361704,
      "count": 43724
    },
    "lilac": {
      "rgb": [
        178.5819270203146,
        122.7690250270649,
        208.67592179838246
      ],
      "hue_angle": 278.9814350820907,
      "count": 15703
    },
    "wine": {
      "rgb": [
        134.1013470173188,
        31.83322642719692,
        69.16549069916613
      ],
      "hue_angle": 338.0974183998595,
      "count": 1559
    },
    "taupe": {
      "rgb": [
        174.80308788598575,
        156.25724465558196,
        114.52375296912113
      ],
      "hue_angle": 41.54009835445436,
      "count": 4210
    },
    "yellow": {
      "rgb": [
        226.5609556871554,
        221.26850906450662,
        54.046786014112946
      ],
      "hue_angle": 58.1593002014805,
      "count": 44073
    },
    "teal": {
      "rgb": [
        56.752555664472766,
        179.16501540400503,
        159.3029337627783
      ],
      "hue_angle": 170.26467647975264,
      "count": 57128
    }
  },
  "centore_centroids": {
    "purple": {
      "munsell": "6.81P 3.53/6.45",
      "hue_angle": 312.516,
      "value": 3.53,
      "chroma": 6.45
    },
    "wine": {
      "munsell": "2.69R 2.98/4.85",
      "hue_angle": 9.684000000000001,
      "value": 2.98,
      "chroma": 4.85
    },
    "rust": {
      "munsell": "9.42R 3.95/7.37",
      "hue_angle": 33.912,
      "value": 3.95,
      "chroma": 7.37
    },
    "pink": {
      "munsell": "0.70R 5.76/7.88",
      "hue_angle": 2.5199999999999996,
      "value": 5.76,
      "chroma": 7.88
    },
    "blue": {
      "munsell": "0.56PB 4.69/4.64",
      "hue_angle": 254.016,
      "value": 4.69,
      "chroma": 4.64
    },
    "rose": {
      "munsell": "0.47R 4.99/7.69",
      "hue_angle": 1.692,
      "value": 4.99,
      "chroma": 7.69
    },
    "gray": {
      "munsell": "9.62P 5.25/0.55",
      "hue_angle": 322.632,
      "value": 5.25,
      "chroma": 0.55
    },
    "beige": {
      "munsell": "6.66YR 6.15/3.40",
      "hue_angle": 59.976,
      "value": 6.15,
      "chroma": 3.4
    },
    "magenta": {
      "munsell": "3.82RP 3.37/9.39",
      "hue_angle": 337.752,
      "value": 3.37,
      "chroma": 9.39
    },
    "teal": {
      "munsell": "1.56B 3.32/4.53",
      "hue_angle": 221.61599999999999,
      "value": 3.32,
      "chroma": 4.53
    },
    "violet": {
      "munsell": "7.00P 3.80/6.16",
      "hue_angle": 313.2,
      "value": 3.8,
      "chroma": 6.16
    },
    "peach": {
      "munsell": "2.89YR 7.03/5.86",
      "hue_angle": 46.404,
      "value": 7.03,
      "chroma": 5.86
    },
    "orange": {
      "munsell": "2.50YR 5.69/8.86",
      "hue_angle": 45.0,
      "value": 5.69,
      "chroma": 8.86
    },
    "mauve": {
      "munsell": "1.19RP 5.15/3.85",
      "hue_angle": 328.284,
      "value": 5.15,
      "chroma": 3.85
    },
    "fuchsia": {
      "munsell": "4.78RP 4.09/10.33",
      "hue_angle": 341.208,
      "value": 4.09,
      "chroma": 10.33
    },
    "white": {
      "munsell": "2.07Y 8.01/2.02",
      "hue_angle": 79.452,
      "value": 8.01,
      "chroma": 2.02
    },
    "aqua": {
      "munsell": "7.44BG 6.18/3.37",
      "hue_angle": 206.784,
      "value": 6.18,
      "chroma": 3.37
    },
    "gold": {
      "munsell": "9.79YR 6.39/7.35",
      "hue_angle": 71.244,
      "value": 6.39,
      "chroma": 7.35
    },
    "red": {
      "munsell": "4.27R 3.79/8.82",
      "hue_angle": 15.371999999999998,
      "value": 3.79,
      "chroma": 8.82
    },
    "coral": {
      "munsell": "6.53R 5.84/8.28",
      "hue_angle": 23.508000000000003,
      "value": 5.84,
      "chroma": 8.28
    },
    "sand": {
      "munsell": "7.60YR 6.26/3.19",
      "hue_angle": 63.36,
      "value": 6.26,
      "chroma": 3.19
    },
    "yellow": {
      "munsell": "2.64Y 7.44/7.98",
      "hue_angle": 81.504,
      "value": 7.44,
      "chroma": 7.98
    },
    "navy": {
      "munsell": "7.26PB 2.11/3.61",
      "hue_angle": 278.136,
      "value": 2.11,
      "chroma": 3.61
    },
    "brown": {
      "munsell": "2.84YR 3.95/3.70",
      "hue_angle": 46.224,
      "value": 3.95,
      "chroma": 3.7
    },
    "taupe": {
      "munsell": "3.25YR 4.68/1.42",
      "hue_angle": 47.7,
      "value": 4.68,
      "chroma": 1.42
    },
    "lilac": {
      "munsell": "7.75P 5.61/4.83",
      "hue_angle": 315.9,
      "value": 5.61,
      "chroma": 4.83
    },
    "lavender": {
      "munsell": "5.61P 5.37/4.79",
      "hue_angle": 308.196,
      "value": 5.37,
      "chroma": 4.79
    },
    "turquoise": {
      "munsell": "1.61B 5.45/5.92",
      "hue_angle": 221.796,
      "value": 5.45,
      "chroma": 5.92
    },
    "tan": {
      "munsell": "6.30YR 5.23/4.07",
      "hue_angle": 58.68,
      "value": 5.23,
      "chroma": 4.07
    },
    "green": {
      "munsell": "2.04G 5.33/4.75",
      "hue_angle": 151.344,
      "value": 5.33,
      "chroma": 4.75
    }
  }
}